{
  "036A-BFB9-1B56-D015": {
    "hardware_id": "036A-BFB9-1B56-D015",
    "user_key": "8T6L-WNYT-FFN2-B657",
    "expiry_date": "GAAA-AABO-PQP8-SJ6S",
    "generated_at": "2025-06-02T02:20:47.937477+00:00"
  },
  "036A-BFB9-1B56-D016": {
    "hardware_id": "036A-BFB9-1B56-D016",
    "user_key": "G0UG-EIAE-98IV-I3YE",
    "expiry_date": "GAAA-AABO-PQPM-MHOL",
    "generated_at": "2025-06-02T02:20:47.992424+00:00"
  },
  "036A-BFB9-1B56-D017": {
    "hardware_id": "036A-BFB9-1B56-D017",
    "user_key": "AKVR-I82I-WHQB-EJ0Q",
    "expiry_date": "GAAA-AABO-PQQA-N85S",
    "generated_at": "2025-06-02T02:20:48.048159+00:00"
  }
}
